MANIFEST.in
readme.rst
setup.cfg
setup.py
mpcouch/__init__.py
mpcouch.egg-info/PKG-INFO
mpcouch.egg-info/SOURCES.txt
mpcouch.egg-info/dependency_links.txt
mpcouch.egg-info/not-zip-safe
mpcouch.egg-info/requires.txt
mpcouch.egg-info/top_level.txt