Metadata-Version: 1.1
Name: mpcouch
Version: 0.2.5
Summary: A multiprocess bulk-uploading helper for CouchDB
Home-page: https://github.com/scubbx/couch-bulk-multiprocess
Author: Markus Mayr
Author-email: markusmayr@gmx.net
License: MIT
Keywords: couchdb multiprocessing upload bulk
Platform: UNKNOWN
Classifier: Programming Language :: Python :: 3.2
Classifier: Topic :: Database
